BDviz/helper_functions.py
BDviz/plotbd.py
bdviz-1.0.1.dist-info/licenses/LICENSE
bdviz-1.0.1.dist-info/METADATA
bdviz-1.0.1.dist-info/WHEEL
bdviz-1.0.1.dist-info/top_level.txt
bdviz-1.0.1.dist-info/RECORD
