Metadata-Version: 2.4
Name: BDviz
Version: 1.0.1
License-File: LICENSE
Requires-Dist: numpy
Requires-Dist: astropy
Requires-Dist: matplotlib
Requires-Dist: astroquery
Requires-Dist: ipympl
Requires-Dist: IPython
Requires-Dist: jupyter
Dynamic: license-file
